snes/__init__.py
snes/evaluate.py
snes/infer.py
snes/train.py
snes/version.py
snes/data/loaders.py
snes/data/preprocess.py
snes/models/metrics.py
snes/models/segmenter.py
snes/utils/io.py
snes/utils/logging.py
snes/utils/seed.py
snes-0.0.1.dist-info/licenses/LICENSE
snes-0.0.1.dist-info/METADATA
snes-0.0.1.dist-info/WHEEL
snes-0.0.1.dist-info/entry_points.txt
snes-0.0.1.dist-info/top_level.txt
snes-0.0.1.dist-info/RECORD
