Metadata-Version: 2.4
Name: snes
Version: 0.0.1
Summary: Simple Narrative Edge Segmenter — a ModernBERT-based scene/chapter boundary detector
Author-email: Mitchell Currie <dev@example.com>
License: MIT
Keywords: nlp,scene-segmentation,longform,modernbert,fiction,story-structure
Classifier: Development Status :: 3 - Alpha
Classifier: Intended Audience :: Developers
Classifier: Topic :: Scientific/Engineering :: Artificial Intelligence
Classifier: License :: OSI Approved :: MIT License
Classifier: Programming Language :: Python :: 3
Requires-Python: >=3.10
License-File: LICENSE
Requires-Dist: torch>=2.1
Requires-Dist: transformers>=4.45
Requires-Dist: datasets>=2.20
Requires-Dist: evaluate>=0.4
Requires-Dist: scikit-learn>=1.4
Requires-Dist: numpy
Requires-Dist: tqdm
Requires-Dist: pyyaml
Dynamic: license-file
